cn_formatter
tests
