Metadata-Version: 2.1
Name: cn-formatter-scanner
Version: 0.6
Summary: This Python package provides a title formatter for cuddlynest properties
Author: M Usman Tahir
Author-email: usman@cuddlynest.com
